invisibleroads_macros_configuration/__init__.py
invisibleroads_macros_configuration/constants.py
invisibleroads_macros_configuration/formats.py
invisibleroads_macros_configuration/settings.py
invisibleroads_macros_configuration-1.0.8.dist-info/METADATA
invisibleroads_macros_configuration-1.0.8.dist-info/WHEEL
invisibleroads_macros_configuration-1.0.8.dist-info/entry_points.txt
invisibleroads_macros_configuration-1.0.8.dist-info/top_level.txt
invisibleroads_macros_configuration-1.0.8.dist-info/RECORD
