Metadata-Version: 2.1
Name: invisibleroads-macros-configuration
Version: 1.0.8
Summary: Shortcut functions for configuration operations
Home-page: https://github.com/invisibleroads/invisibleroads-macros-configuration
Author: Roy Hyunjin Han
Author-email: rhh@crosscompute.com
License: UNKNOWN
Keywords: invisibleroads
Platform: UNKNOWN
Classifier: Programming Language :: Python
Classifier: License :: OSI Approved :: MIT License
Requires-Dist: invisibleroads-macros-log (>=1.0.3)
Requires-Dist: invisibleroads-macros-security (>=1.0.1)
Provides-Extra: test
Requires-Dist: pytest ; extra == 'test'
Requires-Dist: pytest-cov ; extra == 'test'
